Metadata-Version: 1.0
Name: js.angular-ui-scroll
Version: 1.4.1
Summary: Fanstatic packaging of Angular UI scroll
Home-page: UNKNOWN
Author: Fanstatic Developers
Author-email: fanstatic@googlegroups.com
License: BSD
Platform: UNKNOWN
